channels_panel/__init__.py
channels_panel/apps.py
channels_panel/panel.py
channels_panel/routes.py
channels_panel/settings.py
channels_panel/utils.py
channels_panel/static/channels_panel/channels_panel.js
channels_panel/static/channels_panel/reconnecting-websocket.min.js
channels_panel/templates/channels_panel/channels_panel.html
django_channels_panel-0.0.5.dist-info/DESCRIPTION.rst
django_channels_panel-0.0.5.dist-info/METADATA
django_channels_panel-0.0.5.dist-info/RECORD
django_channels_panel-0.0.5.dist-info/WHEEL
django_channels_panel-0.0.5.dist-info/metadata.json
django_channels_panel-0.0.5.dist-info/top_level.txt
