Metadata-Version: 2.0
Name: django-channels-panel
Version: 0.0.5
Summary: A Django Debug Toolbar panel for Channels
Home-page: https://github.com/Krukov/django-channels-panel
Author: Dmitry Krukov
Author-email: glebov.ru@gmail.com
License: MIT
Platform: UNKNOWN
Classifier: Development Status :: 4 - Beta
Classifier: License :: OSI Approved :: MIT License
Classifier: Framework :: Django
Classifier: Intended Audience :: Developers
Classifier: License :: OSI Approved :: MIT License
Classifier: Operating System :: OS Independent
Classifier: Programming Language :: Python
Classifier: Programming Language :: Python :: 2.7
Classifier: Programming Language :: Python :: 3.4
Classifier: Programming Language :: Python :: 3.5
Requires-Dist: django-debug-toolbar
Requires-Dist: channels
